bl_agent_debater-0.2.1.dist-info/licenses/LICENSE
bl_debater/__init__.py
bl_debater/cli.py
bl_debater/debate.py
bl_debater/formatting.py
bl_debater/watch.py
bl_debater/roles/analyzer.md
bl_debater/roles/analyzer.yaml
bl_debater/roles/architect.md
bl_debater/roles/architect.yaml
bl_debater/roles/backend.md
bl_debater/roles/backend.yaml
bl_debater/roles/frontend.md
bl_debater/roles/frontend.yaml
bl_debater/roles/mobile.md
bl_debater/roles/mobile.yaml
bl_debater/roles/performance-auditor.yaml
bl_debater/roles/performance.md
bl_debater/roles/performance.yaml
bl_debater/roles/qa.md
bl_debater/roles/qa.yaml
bl_debater/roles/reviewer.md
bl_debater/roles/reviewer.yaml
bl_debater/roles/security-reviewer.yaml
bl_debater/roles/security.md
bl_debater/roles/security.yaml
bl_agent_debater-0.2.1.dist-info/METADATA
bl_agent_debater-0.2.1.dist-info/WHEEL
bl_agent_debater-0.2.1.dist-info/entry_points.txt
bl_agent_debater-0.2.1.dist-info/top_level.txt
bl_agent_debater-0.2.1.dist-info/RECORD
