Metadata-Version: 2.4
Name: bl-agent-debater
Version: 0.2.1
Summary: CLI for orchestrating structured debates between AI agents
Author-email: Beyond Logic Labs <hello@beyondlogiclabs.com>
License: MIT
Project-URL: Homepage, https://beyondlogics.com/debater
Project-URL: Documentation, https://github.com/beyond-logic-labs/bl-agent-debater#readme
Project-URL: Repository, https://github.com/beyond-logic-labs/bl-agent-debater
Project-URL: Issues, https://github.com/beyond-logic-labs/bl-agent-debater/issues
Keywords: ai,debate,cli,claude,codex,llm
Classifier: Development Status :: 3 - Alpha
Classifier: Environment :: Console
Classifier: Intended Audience :: Developers
Classifier: License :: OSI Approved :: MIT License
Classifier: Operating System :: OS Independent
Classifier: Programming Language :: Python :: 3
Classifier: Programming Language :: Python :: 3.10
Classifier: Programming Language :: Python :: 3.11
Classifier: Programming Language :: Python :: 3.12
Classifier: Topic :: Scientific/Engineering :: Artificial Intelligence
Requires-Python: >=3.10
License-File: LICENSE
Dynamic: license-file
